MANIFEST.in
README.md
setup.py
zabbix_api.py
zabbix_api.egg-info/PKG-INFO
zabbix_api.egg-info/SOURCES.txt
zabbix_api.egg-info/dependency_links.txt
zabbix_api.egg-info/not-zip-safe
zabbix_api.egg-info/top_level.txt