Metadata-Version: 1.1
Name: zabbix-api
Version: 0.5.3
Summary: Zabbix API
Home-page: https://github.com/gescheit/scripts
Author: Aleksandr Balezin
Author-email: gescheit12@gmail.com
License: GNU LGPL 2.1
Platform: any
Classifier: Programming Language :: Python
Classifier: Programming Language :: Python :: 2
Classifier: Programming Language :: Python :: 3
Classifier: Development Status :: 5 - Production/Stable
